<?xml version="1.0" encoding="utf-8" ?>
<dwsync>
<file name="index.html" server="C:/xampp/htdocs/Consultoria/" local="130881112487651248" remote="130881112480000000" />
<file name="registro.php" server="C:/xampp/htdocs/Consultoria/" local="130703108640000000" remote="130703108640000000" />
<file name="informacion.html" server="C:/xampp/htdocs/Consultoria/" local="130703107640000000" remote="130703107640000000" />
<file name="contactanos.php" server="C:/xampp/htdocs/Consultoria/" local="130703109000000000" remote="130703109000000000" />
<file name="usuario.php" server="C:/xampp/htdocs/Consultoria/" local="130697451000000000" remote="130697451000000000" />
<file name="visualizar_solicitud.php" server="C:/xampp/htdocs/Consultoria/" local="130772209408058458" remote="130772209400000000" />
<file name="administrador.php" server="C:/xampp/htdocs/Consultoria/" local="130699080480000000" remote="130699080480000000" />
<file name="administrador_solicitud.php" server="C:/xampp/htdocs/Consultoria/" local="130697391080000000" remote="130697391080000000" />
<file name="administrador_usuario.php" server="C:/xampp/htdocs/Consultoria/" local="130697430760000000" remote="130697430760000000" />
<file name="administrador_empresa.php" server="C:/xampp/htdocs/Consultoria/" local="130697421360000000" remote="130697421360000000" />
<file name="administrador_ramo.php" server="C:/xampp/htdocs/Consultoria/" local="130697425140000000" remote="130697425140000000" />
<file name="administrador_representante.php" server="C:/xampp/htdocs/Consultoria/" local="130697426760000000" remote="130697426760000000" />
<file name="administrador_servicio.php" server="C:/xampp/htdocs/Consultoria/" local="130697428860000000" remote="130697428860000000" />
<file name="visualizar_cotizacion.php" server="C:/xampp/htdocs/Consultoria/" local="130697453980000000" remote="130697453980000000" />
<file name="transicion.swf" server="C:/xampp/htdocs/Consultoria/" local="130683570420000000" remote="130683570420000000" />
<file name="menu_consultoria.swf" server="C:/xampp/htdocs/Consultoria/" local="130693518860000000" remote="130693518860000000" />
<file name="menu_administrador.swf" server="C:/xampp/htdocs/Consultoria/" local="130684122140000000" remote="130684122140000000" />
<file name="boton_salir.swf" server="C:/xampp/htdocs/Consultoria/" local="130683308980000000" remote="130683308980000000" />
<file name="cuadro_contactanos.swf" server="C:/xampp/htdocs/Consultoria/" local="130683758340000000" remote="130683758340000000" />
<file name="invitacion_registrar.swf" server="C:/xampp/htdocs/Consultoria/" local="130683845480000000" remote="130683845480000000" />
<file name="visualizar_documentos.php" server="C:/xampp/htdocs/Consultoria/" local="130697456520000000" remote="130697456520000000" />
<file name="administrador_documentos.php" server="C:/xampp/htdocs/Consultoria/" local="130697422400000000" remote="130697422400000000" />
<file name="registro2.php" server="C:/xampp/htdocs/Consultoria/" local="130703108900000000" remote="130703108900000000" />
<file name="usuario2.php" server="C:/xampp/htdocs/Consultoria/" local="130697458880000000" remote="130697458880000000" />
<file name="transicion.swf" server="C:/xampp/htdocs/Consultoria" local="130683570420000000" remote="130683570420000000" />
<file name="menu_consultoria.swf" server="C:/xampp/htdocs/Consultoria" local="130693518860000000" remote="130693518860000000" />
<file name="invitacion_registrar.swf" server="C:/xampp/htdocs/Consultoria" local="130683845480000000" remote="130683845480000000" />
<file name="index.html" server="C:/xampp/htdocs/Consultoria" local="130703106800000000" remote="130703106800000000" />
<file name="Thumbs.db" server="C:/xampp/htdocs/Consultoria/" local="130681392120000000" remote="130681392120000000" />
<file name="consultor.php" server="C:/xampp/htdocs/Consultoria/" local="130697432060000000" remote="130697432060000000" />
<file name="consultor_solicitud.php" server="C:/xampp/htdocs/Consultoria/" local="130697392460000000" remote="130697392460000000" />
<file name="consultor_documentos.php" server="C:/xampp/htdocs/Consultoria/" local="130697434100000000" remote="130697434100000000" />
</dwsync>